{
  "type": "Feature",
  "properties": {
    "gn:admin1_code":"00",
    "gn:asciiname":"Hasi Chor",
    "gn:country_code":"EH",
    "gn:dem":266,
    "gn:feature_class":"P",
    "gn:feature_code":"PPL",
    "gn:name":"Hasi Chor",
    "gn:population":0,
    "gn:timezone":"Africa/El_Aaiun",
    "iso:country":"EH",
    "wof:name":"Hasi Chor",
    "wof:placetype":"locality"
},
  "geometry": {"coordinates":[-13.01338,21.29987],"type":"Point"}
}